CHANGES.txt
LICENSE.txt
MANIFEST.in
README.rst
setup.py
aioes/__init__.py
aioes/connection.py
aioes/exception.py
aioes/log.py
aioes/pool.py
aioes/transport.py
aioes/client/__init__.py
aioes/client/cat.py
aioes/client/cluster.py
aioes/client/indices.py
aioes/client/nodes.py
aioes/client/snapshot.py
aioes/client/utils.py
aioes_ext.egg-info/PKG-INFO
aioes_ext.egg-info/SOURCES.txt
aioes_ext.egg-info/dependency_links.txt
aioes_ext.egg-info/requires.txt
aioes_ext.egg-info/top_level.txt
docs/Makefile
docs/conf.py
docs/glossary.rst
docs/index.rst
docs/make.bat
docs/reference.rst
tests/conftest.py
tests/test_cat.py
tests/test_client.py
tests/test_cluster.py
tests/test_connection.py
tests/test_indices.py
tests/test_nodes.py
tests/test_pool.py
tests/test_snapshot.py
tests/test_transport.py
tests/repo/.gitignore