Metadata-Version: 1.1
Name: aioes-ext
Version: 0.6.2
Summary: Elasticsearch integration with asyncio.
Home-page: http://aioes.readthedocs.org
Author: Andrew Svetlov
Author-email: andrew.svetlov@gmail.com
License: Apache 2
Platform: POSIX
Classifier: License :: OSI Approved :: BSD License
Classifier: Intended Audience :: Developers
Classifier: Programming Language :: Python :: 3
Classifier: Programming Language :: Python :: 3.4
Classifier: Programming Language :: Python :: 3.5
Classifier: Operating System :: POSIX
Classifier: Operating System :: MacOS :: MacOS X
Classifier: Environment :: Web Environment
Classifier: Development Status :: 4 - Beta
Classifier: Topic :: Database
Classifier: Topic :: Database :: Front-Ends
